setup.py
piy/__init__.py
piy/piy.py
piy.egg-info/PKG-INFO
piy.egg-info/SOURCES.txt
piy.egg-info/dependency_links.txt
piy.egg-info/entry_points.txt
piy.egg-info/requires.txt
piy.egg-info/top_level.txt