Metadata-Version: 1.1
Name: piy
Version: 0.0.1
Summary: POM in YAML
Home-page: http://github.com/wikier/piy
Author: Sergio Fernández
Author-email: sergio@wikier.org
License: UNKNOWN
Platform: UNKNOWN
Classifier: Development Status :: 3 - Alpha
Classifier: Environment :: Console
Classifier: Intended Audience :: Developers
Classifier: License :: OSI Approved :: GNU General Public License v3 or later (GPLv3+)
Classifier: Operating System :: OS Independent
Classifier: Programming Language :: Python
Classifier: Topic :: Utilities
Requires: pyyaml
Requires: hutools
